catlive_app_helper/__init__.py
catlive_app_helper/info.py
catlive_app_helper/api/__init__.py
catlive_app_helper/api/page/__init__.py
catlive_app_helper/api/page/chat.py
catlive_app_helper/api/page/emoji.py
catlive_app_helper/api/page/favorite.py
catlive_app_helper/api/page/portal.py
catlive_app_helper/api/page/my/__init__.py
catlive_app_helper/api/page/my/my.py
catlive_app_helper/api/page/my/settings.py
catlive_app_helper/api/page/popup/__init__.py
catlive_app_helper/api/page/popup/gift.py
catlive_app_helper/api/page/room/__init__.py
catlive_app_helper/api/page/room/voice_room.py
catlive_app_helper-0.0.9.dist-info/LICENSE
catlive_app_helper-0.0.9.dist-info/METADATA
catlive_app_helper-0.0.9.dist-info/WHEEL
catlive_app_helper-0.0.9.dist-info/top_level.txt
catlive_app_helper-0.0.9.dist-info/RECORD
