Metadata-Version: 2.1
Name: catlive-app-helper
Version: 0.0.9
Summary: This is my catlive app helper package
Home-page: https://github.com/ckf10000/catlive-app-helper
Author: ckf10000
Author-email: ckf10000@sina.com
Classifier: Programming Language :: Python :: 3
Classifier: License :: OSI Approved :: MIT License
Classifier: Operating System :: OS Independent
License-File: LICENSE
Requires-Dist: airtest-helper >=0.1.1
